{"nodes": [{"id": "c_users_danielsargunar_onedrive_documents_github_edenailabs_paytm_ai_hackathon_graphify_corpus_app_n8n_ts", "label": "n8n.ts", "file_type": "code", "source_file": "C:\\Users\\danielsargunar\\OneDrive\\Documents\\GitHub\\edenailabs-paytm-ai-hackathon\\graphify-corpus\\app\\n8n.ts", "source_location": "L1"}, {"id": "n8n_calln8n", "label": "callN8n()", "file_type": "code", "source_file": "C:\\Users\\danielsargunar\\OneDrive\\Documents\\GitHub\\edenailabs-paytm-ai-hackathon\\graphify-corpus\\app\\n8n.ts", "source_location": "L10"}, {"id": "n8n_getjwt", "label": "getJwt()", "file_type": "code", "source_file": "C:\\Users\\danielsargunar\\OneDrive\\Documents\\GitHub\\edenailabs-paytm-ai-hackathon\\graphify-corpus\\app\\n8n.ts", "source_location": "L41"}, {"id": "n8n_discoverleads", "label": "discoverLeads()", "file_type": "code", "source_file": "C:\\Users\\danielsargunar\\OneDrive\\Documents\\GitHub\\edenailabs-paytm-ai-hackathon\\graphify-corpus\\app\\n8n.ts", "source_location": "L47"}, {"id": "n8n_generateoutreach", "label": "generateOutreach()", "file_type": "code", "source_file": "C:\\Users\\danielsargunar\\OneDrive\\Documents\\GitHub\\edenailabs-paytm-ai-hackathon\\graphify-corpus\\app\\n8n.ts", "source_location": "L68"}, {"id": "n8n_generatewebsite", "label": "generateWebsite()", "file_type": "code", "source_file": "C:\\Users\\danielsargunar\\OneDrive\\Documents\\GitHub\\edenailabs-paytm-ai-hackathon\\graphify-corpus\\app\\n8n.ts", "source_location": "L87"}, {"id": "n8n_updatepipeline", "label": "updatePipeline()", "file_type": "code", "source_file": "C:\\Users\\danielsargunar\\OneDrive\\Documents\\GitHub\\edenailabs-paytm-ai-hackathon\\graphify-corpus\\app\\n8n.ts", "source_location": "L102"}, {"id": "n8n_generatestrategy", "label": "generateStrategy()", "file_type": "code", "source_file": "C:\\Users\\danielsargunar\\OneDrive\\Documents\\GitHub\\edenailabs-paytm-ai-hackathon\\graphify-corpus\\app\\n8n.ts", "source_location": "L119"}, {"id": "n8n_sendsms", "label": "sendSms()", "file_type": "code", "source_file": "C:\\Users\\danielsargunar\\OneDrive\\Documents\\GitHub\\edenailabs-paytm-ai-hackathon\\graphify-corpus\\app\\n8n.ts", "source_location": "L132"}, {"id": "n8n_sendwhatsapp", "label": "sendWhatsApp()", "file_type": "code", "source_file": "C:\\Users\\danielsargunar\\OneDrive\\Documents\\GitHub\\edenailabs-paytm-ai-hackathon\\graphify-corpus\\app\\n8n.ts", "source_location": "L151"}, {"id": "n8n_logcall", "label": "logCall()", "file_type": "code", "source_file": "C:\\Users\\danielsargunar\\OneDrive\\Documents\\GitHub\\edenailabs-paytm-ai-hackathon\\graphify-corpus\\app\\n8n.ts", "source_location": "L172"}], "edges": [{"source": "c_users_danielsargunar_onedrive_documents_github_edenailabs_paytm_ai_hackathon_graphify_corpus_app_n8n_ts", "target": "n8n_calln8n", "relation": "contains", "confidence": "EXTRACTED", "source_file": "C:\\Users\\danielsargunar\\OneDrive\\Documents\\GitHub\\edenailabs-paytm-ai-hackathon\\graphify-corpus\\app\\n8n.ts", "source_location": "L10", "weight": 1.0}, {"source": "c_users_danielsargunar_onedrive_documents_github_edenailabs_paytm_ai_hackathon_graphify_corpus_app_n8n_ts", "target": "client", "relation": "imports_from", "confidence": "EXTRACTED", "source_file": "C:\\Users\\danielsargunar\\OneDrive\\Documents\\GitHub\\edenailabs-paytm-ai-hackathon\\graphify-corpus\\app\\n8n.ts", "source_location": "L39", "weight": 1.0}, {"source": "c_users_danielsargunar_onedrive_documents_github_edenailabs_paytm_ai_hackathon_graphify_corpus_app_n8n_ts", "target": "n8n_getjwt", "relation": "contains", "confidence": "EXTRACTED", "source_file": "C:\\Users\\danielsargunar\\OneDrive\\Documents\\GitHub\\edenailabs-paytm-ai-hackathon\\graphify-corpus\\app\\n8n.ts", "source_location": "L41", "weight": 1.0}, {"source": "c_users_danielsargunar_onedrive_documents_github_edenailabs_paytm_ai_hackathon_graphify_corpus_app_n8n_ts", "target": "n8n_discoverleads", "relation": "contains", "confidence": "EXTRACTED", "source_file": "C:\\Users\\danielsargunar\\OneDrive\\Documents\\GitHub\\edenailabs-paytm-ai-hackathon\\graphify-corpus\\app\\n8n.ts", "source_location": "L47", "weight": 1.0}, {"source": "c_users_danielsargunar_onedrive_documents_github_edenailabs_paytm_ai_hackathon_graphify_corpus_app_n8n_ts", "target": "n8n_generateoutreach", "relation": "contains", "confidence": "EXTRACTED", "source_file": "C:\\Users\\danielsargunar\\OneDrive\\Documents\\GitHub\\edenailabs-paytm-ai-hackathon\\graphify-corpus\\app\\n8n.ts", "source_location": "L68", "weight": 1.0}, {"source": "c_users_danielsargunar_onedrive_documents_github_edenailabs_paytm_ai_hackathon_graphify_corpus_app_n8n_ts", "target": "n8n_generatewebsite", "relation": "contains", "confidence": "EXTRACTED", "source_file": "C:\\Users\\danielsargunar\\OneDrive\\Documents\\GitHub\\edenailabs-paytm-ai-hackathon\\graphify-corpus\\app\\n8n.ts", "source_location": "L87", "weight": 1.0}, {"source": "c_users_danielsargunar_onedrive_documents_github_edenailabs_paytm_ai_hackathon_graphify_corpus_app_n8n_ts", "target": "n8n_updatepipeline", "relation": "contains", "confidence": "EXTRACTED", "source_file": "C:\\Users\\danielsargunar\\OneDrive\\Documents\\GitHub\\edenailabs-paytm-ai-hackathon\\graphify-corpus\\app\\n8n.ts", "source_location": "L102", "weight": 1.0}, {"source": "c_users_danielsargunar_onedrive_documents_github_edenailabs_paytm_ai_hackathon_graphify_corpus_app_n8n_ts", "target": "n8n_generatestrategy", "relation": "contains", "confidence": "EXTRACTED", "source_file": "C:\\Users\\danielsargunar\\OneDrive\\Documents\\GitHub\\edenailabs-paytm-ai-hackathon\\graphify-corpus\\app\\n8n.ts", "source_location": "L119", "weight": 1.0}, {"source": "c_users_danielsargunar_onedrive_documents_github_edenailabs_paytm_ai_hackathon_graphify_corpus_app_n8n_ts", "target": "n8n_sendsms", "relation": "contains", "confidence": "EXTRACTED", "source_file": "C:\\Users\\danielsargunar\\OneDrive\\Documents\\GitHub\\edenailabs-paytm-ai-hackathon\\graphify-corpus\\app\\n8n.ts", "source_location": "L132", "weight": 1.0}, {"source": "c_users_danielsargunar_onedrive_documents_github_edenailabs_paytm_ai_hackathon_graphify_corpus_app_n8n_ts", "target": "n8n_sendwhatsapp", "relation": "contains", "confidence": "EXTRACTED", "source_file": "C:\\Users\\danielsargunar\\OneDrive\\Documents\\GitHub\\edenailabs-paytm-ai-hackathon\\graphify-corpus\\app\\n8n.ts", "source_location": "L151", "weight": 1.0}, {"source": "c_users_danielsargunar_onedrive_documents_github_edenailabs_paytm_ai_hackathon_graphify_corpus_app_n8n_ts", "target": "n8n_logcall", "relation": "contains", "confidence": "EXTRACTED", "source_file": "C:\\Users\\danielsargunar\\OneDrive\\Documents\\GitHub\\edenailabs-paytm-ai-hackathon\\graphify-corpus\\app\\n8n.ts", "source_location": "L172", "weight": 1.0}, {"source": "n8n_discoverleads", "target": "n8n_getjwt", "relation": "calls", "confidence": "EXTRACTED", "source_file": "C:\\Users\\danielsargunar\\OneDrive\\Documents\\GitHub\\edenailabs-paytm-ai-hackathon\\graphify-corpus\\app\\n8n.ts", "source_location": "L53", "weight": 1.0}, {"source": "n8n_discoverleads", "target": "n8n_calln8n", "relation": "calls", "confidence": "EXTRACTED", "source_file": "C:\\Users\\danielsargunar\\OneDrive\\Documents\\GitHub\\edenailabs-paytm-ai-hackathon\\graphify-corpus\\app\\n8n.ts", "source_location": "L54", "weight": 1.0}, {"source": "n8n_generateoutreach", "target": "n8n_getjwt", "relation": "calls", "confidence": "EXTRACTED", "source_file": "C:\\Users\\danielsargunar\\OneDrive\\Documents\\GitHub\\edenailabs-paytm-ai-hackathon\\graphify-corpus\\app\\n8n.ts", "source_location": "L75", "weight": 1.0}, {"source": "n8n_generateoutreach", "target": "n8n_calln8n", "relation": "calls", "confidence": "EXTRACTED", "source_file": "C:\\Users\\danielsargunar\\OneDrive\\Documents\\GitHub\\edenailabs-paytm-ai-hackathon\\graphify-corpus\\app\\n8n.ts", "source_location": "L76", "weight": 1.0}, {"source": "n8n_generatewebsite", "target": "n8n_getjwt", "relation": "calls", "confidence": "EXTRACTED", "source_file": "C:\\Users\\danielsargunar\\OneDrive\\Documents\\GitHub\\edenailabs-paytm-ai-hackathon\\graphify-corpus\\app\\n8n.ts", "source_location": "L92", "weight": 1.0}, {"source": "n8n_generatewebsite", "target": "n8n_calln8n", "relation": "calls", "confidence": "EXTRACTED", "source_file": "C:\\Users\\danielsargunar\\OneDrive\\Documents\\GitHub\\edenailabs-paytm-ai-hackathon\\graphify-corpus\\app\\n8n.ts", "source_location": "L93", "weight": 1.0}, {"source": "n8n_updatepipeline", "target": "n8n_getjwt", "relation": "calls", "confidence": "EXTRACTED", "source_file": "C:\\Users\\danielsargunar\\OneDrive\\Documents\\GitHub\\edenailabs-paytm-ai-hackathon\\graphify-corpus\\app\\n8n.ts", "source_location": "L108", "weight": 1.0}, {"source": "n8n_updatepipeline", "target": "n8n_calln8n", "relation": "calls", "confidence": "EXTRACTED", "source_file": "C:\\Users\\danielsargunar\\OneDrive\\Documents\\GitHub\\edenailabs-paytm-ai-hackathon\\graphify-corpus\\app\\n8n.ts", "source_location": "L109", "weight": 1.0}, {"source": "n8n_generatestrategy", "target": "n8n_getjwt", "relation": "calls", "confidence": "EXTRACTED", "source_file": "C:\\Users\\danielsargunar\\OneDrive\\Documents\\GitHub\\edenailabs-paytm-ai-hackathon\\graphify-corpus\\app\\n8n.ts", "source_location": "L123", "weight": 1.0}, {"source": "n8n_generatestrategy", "target": "n8n_calln8n", "relation": "calls", "confidence": "EXTRACTED", "source_file": "C:\\Users\\danielsargunar\\OneDrive\\Documents\\GitHub\\edenailabs-paytm-ai-hackathon\\graphify-corpus\\app\\n8n.ts", "source_location": "L124", "weight": 1.0}, {"source": "n8n_sendsms", "target": "n8n_getjwt", "relation": "calls", "confidence": "EXTRACTED", "source_file": "C:\\Users\\danielsargunar\\OneDrive\\Documents\\GitHub\\edenailabs-paytm-ai-hackathon\\graphify-corpus\\app\\n8n.ts", "source_location": "L139", "weight": 1.0}, {"source": "n8n_sendsms", "target": "n8n_calln8n", "relation": "calls", "confidence": "EXTRACTED", "source_file": "C:\\Users\\danielsargunar\\OneDrive\\Documents\\GitHub\\edenailabs-paytm-ai-hackathon\\graphify-corpus\\app\\n8n.ts", "source_location": "L140", "weight": 1.0}, {"source": "n8n_sendwhatsapp", "target": "n8n_getjwt", "relation": "calls", "confidence": "EXTRACTED", "source_file": "C:\\Users\\danielsargunar\\OneDrive\\Documents\\GitHub\\edenailabs-paytm-ai-hackathon\\graphify-corpus\\app\\n8n.ts", "source_location": "L159", "weight": 1.0}, {"source": "n8n_sendwhatsapp", "target": "n8n_calln8n", "relation": "calls", "confidence": "EXTRACTED", "source_file": "C:\\Users\\danielsargunar\\OneDrive\\Documents\\GitHub\\edenailabs-paytm-ai-hackathon\\graphify-corpus\\app\\n8n.ts", "source_location": "L160", "weight": 1.0}, {"source": "n8n_logcall", "target": "n8n_getjwt", "relation": "calls", "confidence": "EXTRACTED", "source_file": "C:\\Users\\danielsargunar\\OneDrive\\Documents\\GitHub\\edenailabs-paytm-ai-hackathon\\graphify-corpus\\app\\n8n.ts", "source_location": "L181", "weight": 1.0}, {"source": "n8n_logcall", "target": "n8n_calln8n", "relation": "calls", "confidence": "EXTRACTED", "source_file": "C:\\Users\\danielsargunar\\OneDrive\\Documents\\GitHub\\edenailabs-paytm-ai-hackathon\\graphify-corpus\\app\\n8n.ts", "source_location": "L182", "weight": 1.0}], "raw_calls": [{"caller_nid": "n8n_calln8n", "callee": "replace", "source_file": "C:\\Users\\danielsargunar\\OneDrive\\Documents\\GitHub\\edenailabs-paytm-ai-hackathon\\graphify-corpus\\app\\n8n.ts", "source_location": "L18"}, {"caller_nid": "n8n_calln8n", "callee": "log", "source_file": "C:\\Users\\danielsargunar\\OneDrive\\Documents\\GitHub\\edenailabs-paytm-ai-hackathon\\graphify-corpus\\app\\n8n.ts", "source_location": "L19"}, {"caller_nid": "n8n_calln8n", "callee": "stringify", "source_file": "C:\\Users\\danielsargunar\\OneDrive\\Documents\\GitHub\\edenailabs-paytm-ai-hackathon\\graphify-corpus\\app\\n8n.ts", "source_location": "L19"}, {"caller_nid": "n8n_calln8n", "callee": "fetch", "source_file": "C:\\Users\\danielsargunar\\OneDrive\\Documents\\GitHub\\edenailabs-paytm-ai-hackathon\\graphify-corpus\\app\\n8n.ts", "source_location": "L21"}, {"caller_nid": "n8n_calln8n", "callee": "stringify", "source_file": "C:\\Users\\danielsargunar\\OneDrive\\Documents\\GitHub\\edenailabs-paytm-ai-hackathon\\graphify-corpus\\app\\n8n.ts", "source_location": "L24"}, {"caller_nid": "n8n_calln8n", "callee": "text", "source_file": "C:\\Users\\danielsargunar\\OneDrive\\Documents\\GitHub\\edenailabs-paytm-ai-hackathon\\graphify-corpus\\app\\n8n.ts", "source_location": "L28"}, {"caller_nid": "n8n_calln8n", "callee": "error", "source_file": "C:\\Users\\danielsargunar\\OneDrive\\Documents\\GitHub\\edenailabs-paytm-ai-hackathon\\graphify-corpus\\app\\n8n.ts", "source_location": "L29"}, {"caller_nid": "n8n_calln8n", "callee": "text", "source_file": "C:\\Users\\danielsargunar\\OneDrive\\Documents\\GitHub\\edenailabs-paytm-ai-hackathon\\graphify-corpus\\app\\n8n.ts", "source_location": "L33"}, {"caller_nid": "n8n_calln8n", "callee": "parse", "source_file": "C:\\Users\\danielsargunar\\OneDrive\\Documents\\GitHub\\edenailabs-paytm-ai-hackathon\\graphify-corpus\\app\\n8n.ts", "source_location": "L35"}, {"caller_nid": "n8n_getjwt", "callee": "getSession", "source_file": "C:\\Users\\danielsargunar\\OneDrive\\Documents\\GitHub\\edenailabs-paytm-ai-hackathon\\graphify-corpus\\app\\n8n.ts", "source_location": "L42"}]}